iotools/__init__.py
iotools/gui/__init__.py
iotools/gui/argsgui.py
iotools/gui/gui.py
iotools/gui/schedule.py
iotools/gui/widget.py
iotools/handler/__init__.py
iotools/handler/argparser.py
iotools/handler/clink.py
iotools/handler/iohandler.py
iotools/handler/synchronizer.py
iotools/misc/__init__.py
iotools/misc/cache.py
iotools/misc/config.py
iotools/misc/console.py
iotools/misc/log.py
iotools/misc/schedule.py
iotools/misc/script.py
iotools/misc/serializer.py
iotools/misc/validator.py
iotools/res/__init__.py
pyiotools-0.3.18.dist-info/LICENSE
pyiotools-0.3.18.dist-info/METADATA
pyiotools-0.3.18.dist-info/WHEEL
pyiotools-0.3.18.dist-info/top_level.txt
pyiotools-0.3.18.dist-info/RECORD
