Metadata-Version: 2.1
Name: pyiotools
Version: 0.3.18
Summary: Provides several utilities for handling I/O
Home-page: https://github.com/matthewgdv/iotools
Author: Matt GdV
Author-email: matthewgdv@gmail.com
License: MIT
Platform: UNKNOWN
Classifier: Development Status :: 3 - Alpha
Classifier: Intended Audience :: Developers
Classifier: Programming Language :: Python :: 3.8
